{"chunk_definitions":[{"row":115,"row_count":1,"visible":true,"expansion_state":0,"options":{"engine":"r","include":false,"label":"unnamed-chunk-29"},"document_id":"E500FC48","chunk_id":"ckc0mptvhthdv","chunk_label":"unnamed-chunk-1"},{"row":185,"row_count":1,"visible":true,"expansion_state":0,"options":{"engine":"r","include":false,"label":"unnamed-chunk-30"},"document_id":"E500FC48","chunk_id":"cny3pwy6unacw","chunk_label":"unnamed-chunk-4"},{"row":480,"row_count":1,"visible":true,"expansion_state":0,"options":{"engine":"r","include":false,"label":"unnamed-chunk-32"},"document_id":"E500FC48","chunk_id":"c4svuh6wzw0ou","chunk_label":"unnamed-chunk-13"}],"doc_write_time":1634116563}