{"chunk_definitions":[{"row":108,"row_count":1,"visible":true,"expansion_state":0,"options":{"engine":"r","include":false,"label":"unnamed-chunk-130"},"document_id":"198EDE6F","chunk_id":"c8i3qa3d63pja","chunk_label":"unnamed-chunk-1"},{"row":142,"row_count":1,"visible":true,"expansion_state":0,"options":{"engine":"r","include":false,"label":"unnamed-chunk-131"},"document_id":"198EDE6F","chunk_id":"cq2es1hc2x3h9","chunk_label":"unnamed-chunk-2"},{"row":231,"row_count":1,"visible":true,"expansion_state":0,"options":{"engine":"r","include":false,"label":"unnamed-chunk-132"},"document_id":"198EDE6F","chunk_id":"c4c3l18sqvitn","chunk_label":"unnamed-chunk-3"},{"row":280,"row_count":1,"visible":true,"expansion_state":0,"options":{"engine":"r","include":false,"label":"unnamed-chunk-133"},"document_id":"198EDE6F","chunk_id":"c5oa4t6ftxtnq","chunk_label":"unnamed-chunk-4"},{"row":349,"row_count":1,"visible":true,"expansion_state":0,"options":{"engine":"r","include":false,"label":"unnamed-chunk-134"},"document_id":"198EDE6F","chunk_id":"c4oxvad7i26jp","chunk_label":"unnamed-chunk-5"},{"row":393,"row_count":1,"visible":true,"expansion_state":0,"options":{"engine":"r","eval":true,"warning":false,"echo":false,"label":"unnamed-chunk-140"},"document_id":"198EDE6F","chunk_id":"c7xogxspq6ahc","chunk_label":"unnamed-chunk-6"},{"row":455,"row_count":1,"visible":true,"expansion_state":0,"options":{"engine":"r","warning":false,"echo":false,"label":"unnamed-chunk-141"},"document_id":"198EDE6F","chunk_id":"cm91caf4hp1uv","chunk_label":"unnamed-chunk-8"},{"row":508,"row_count":1,"visible":true,"expansion_state":0,"options":{"engine":"r","include":false,"label":"unnamed-chunk-142"},"document_id":"198EDE6F","chunk_id":"cu4ft9bcaj1nq","chunk_label":"unnamed-chunk-9"},{"row":600,"row_count":1,"visible":true,"expansion_state":0,"options":{"engine":"r","eval":true,"warning":false,"echo":false,"label":"unnamed-chunk-143"},"document_id":"198EDE6F","chunk_id":"cw0v0l4o519r0","chunk_label":"unnamed-chunk-11"}],"doc_write_time":1675155811}